timedpool/__init__.py
timedpool/timedpool.py
timedpool-0.1.1.dist-info/LICENSE
timedpool-0.1.1.dist-info/METADATA
timedpool-0.1.1.dist-info/WHEEL
timedpool-0.1.1.dist-info/top_level.txt
timedpool-0.1.1.dist-info/RECORD
