Metadata-Version: 2.1
Name: timedpool
Version: 0.1.1
Summary: Python library adding a dictionary with a maximum size and whose elements are deleted after a delay
Home-page: https://github.com/giubots/timedpool
Author: giubots
Author-email: giubots@protonmail.com
License: UNKNOWN
Project-URL: Bug Tracker, https://github.com/giubots/timedpool/issues
Platform: UNKNOWN
Classifier: Development Status :: 4 - Beta
Classifier: Intended Audience :: Developers
Classifier: License :: OSI Approved :: GNU General Public License v3 (GPLv3)
Classifier: Operating System :: OS Independent
Classifier: Programming Language :: Python :: 3
Classifier: Typing :: Typed
Requires-Python: >=3.6
License-File: LICENSE
